optinterp/__init__.py
optinterp/initial_guesses.py
optinterp/node_finder.py
optinterp/solver.py
optinterp-0.1.0.dist-info/LICENSE.txt
optinterp-0.1.0.dist-info/METADATA
optinterp-0.1.0.dist-info/WHEEL
optinterp-0.1.0.dist-info/top_level.txt
optinterp-0.1.0.dist-info/RECORD
