Metadata-Version: 2.1
Name: optinterp
Version: 0.1.0
Summary: Optimal Interpolation Nodes
Home-page: https://github.com/rustygentile/optinterp
Author: Rusty Gentile
License: UNKNOWN
Project-URL: Source, https://github.com/rustygentile/optinterp
Keywords: interpolation,approximation,curve fitting
Platform: UNKNOWN
Classifier: Development Status :: 3 - Alpha
Classifier: Intended Audience :: Science/Research
Classifier: Topic :: Scientific/Engineering
Classifier: Topic :: Scientific/Engineering :: Mathematics
Classifier: License :: OSI Approved :: MIT License
Classifier: Programming Language :: Python :: 3
Classifier: Programming Language :: Python :: 3.6
Classifier: Programming Language :: Python :: 3.7
Classifier: Programming Language :: Python :: 3.8
Classifier: Programming Language :: Python :: 3.9
Classifier: Programming Language :: Python :: 3 :: Only
Requires-Python: >=3.6, <4
Requires-Dist: scipy (>=1.0.0)
